leddite/__init__.py
leddite/__main__.py
leddite/cli.py
leddite-0.1.11.dist-info/LICENSE
leddite-0.1.11.dist-info/METADATA
leddite-0.1.11.dist-info/WHEEL
leddite-0.1.11.dist-info/entry_points.txt
leddite-0.1.11.dist-info/top_level.txt
leddite-0.1.11.dist-info/RECORD
