Metadata-Version: 2.1
Name: leddite
Version: 0.1.11
Summary: leddite lets you create your own art with Neopixel displays easily
Home-page: https://github.com/adishy/leddite
Author: Aditya Shylesh
Author-email: development-mails@adishy.com
Classifier: Programming Language :: Python :: 3
Classifier: License :: OSI Approved :: MIT License
Classifier: Operating System :: OS Independent
Requires-Python: >=3.6
License-File: LICENSE
Requires-Dist: docopt
Requires-Dist: python-dotenv
Requires-Dist: arrow (==0.15.5)
Requires-Dist: bs4 (==0.0.1)
Requires-Dist: Flask
Requires-Dist: requests (==2.22.0)
Requires-Dist: sh (==1.12.14)
Requires-Dist: rich
